meshx/__about__.py
meshx/__init__.py
meshx/_cli.py
meshx/_helpers.py
meshx-1.2.dist-info/LICENSE
meshx-1.2.dist-info/METADATA
meshx-1.2.dist-info/WHEEL
meshx-1.2.dist-info/entry_points.txt
meshx-1.2.dist-info/top_level.txt
meshx-1.2.dist-info/RECORD
